LICENSE
README.md
setup.py
agents/__init__.py
agents/admin.py
agents/apps.py
agents/models.py
agents/tests.py
agents/urls.py
agents/views.py
bin/dbm-center
dbm_center.egg-info/PKG-INFO
dbm_center.egg-info/SOURCES.txt
dbm_center.egg-info/dependency_links.txt
dbm_center.egg-info/requires.txt
dbm_center.egg-info/top_level.txt
dbmcenter/__init__.py
dbmcenter/asgi.py
dbmcenter/consts.py
dbmcenter/settings.py
dbmcenter/urls.py
dbmcenter/wsgi.py
dbmcenter/core/__init__.py
dbmcenter/core/tasks/__init__.py
dbmcenter/core/tasks/base.py
dbmcenter/core/tasks/master.py
dbmcenter/dbm-center/favicon.ico
dbmcenter/dbm-center/index.html
dbmcenter/dbm-center/css/app.940106bb.css
dbmcenter/dbm-center/js/app.4bb2602a.js
dbmcenter/dbm-center/js/app.4bb2602a.js.map
dbmcenter/dbm-center/js/chunk-vendors.ae02e612.js
dbmcenter/dbm-center/js/chunk-vendors.ae02e612.js.map
dbmcenter/views/__init__.py
dbmcenter/views/configs.py